lbptoolspy/__init__.py
lbptoolspy/binary_files.py
lbptoolspy/far4_tools.py
lbptoolspy/image_helpers.py
lbptoolspy/images_to_mod.py
lbptoolspy/jsonify_lbp_files.py
lbptoolspy/l0_dec_enc.py
lbptoolspy/mod_installer.py
lbptoolspy/tex_tools.py
lbptoolspy-1.3.0.dist-info/METADATA
lbptoolspy-1.3.0.dist-info/WHEEL
lbptoolspy-1.3.0.dist-info/licenses/LICENSE
lbptoolspy-1.3.0.dist-info/RECORD
