Metadata-Version: 2.4
Name: lbptoolspy
Version: 1.3.0
Summary: Tools used to interface with files and saves from LittleBigPlanet series
Project-URL: Homepage, https://github.com/Zhaxxy/lbptoolspy/
Project-URL: Issues, https://github.com/Zhaxxy/lbptoolspy/issues
Author-email: Zhaxxy <superyahya03@gmail.com>
License:                     GNU GENERAL PUBLIC LICENSE
License-File: LICENSE
Classifier: License :: OSI Approved :: GNU General Public License v3 (GPLv3)
Classifier: Operating System :: OS Independent
Classifier: Programming Language :: Python :: 3
Requires-Python: >=3.11
Requires-Dist: pillow
Requires-Dist: xxtea
